optolink2mqtt/__init__.py
optolink2mqtt/_optolink2mqtt_version.py
optolink2mqtt/config.py
optolink2mqtt/ha_support.py
optolink2mqtt/ha_units.py
optolink2mqtt/main.py
optolink2mqtt/mqtt_client.py
optolink2mqtt/optolink2mqtt_app.py
optolink2mqtt/optolinkvs2_protocol.py
optolink2mqtt/optolinkvs2_register.py
optolink2mqtt/schema/optolink2mqtt.schema.yaml
viessmann_optolink2mqtt-1.2.0.dist-info/METADATA
viessmann_optolink2mqtt-1.2.0.dist-info/WHEEL
viessmann_optolink2mqtt-1.2.0.dist-info/entry_points.txt
viessmann_optolink2mqtt-1.2.0.dist-info/licenses/LICENSE
viessmann_optolink2mqtt-1.2.0.dist-info/RECORD
