Metadata-Version: 2.4
Name: viessmann-optolink2mqtt
Version: 1.2.0
Summary: Open source interface between a Viessmann device (heat pump, gas heater, etc) and MQTT
Project-URL: Homepage, https://github.com/f18m/viessmann-optolink2mqtt
Project-URL: Bug Tracker, https://github.com/f18m/viessmann-optolink2mqtt/issues
Author: Phil
Author-email: Francesco Montorsi <francesco.montorsi.nospam@gmail.com>
License-File: LICENSE
Classifier: License :: OSI Approved :: MIT License
Classifier: Operating System :: OS Independent
Classifier: Programming Language :: Python :: 3
Requires-Python: >=3.9
Requires-Dist: paho-mqtt==2.1.0
Requires-Dist: platformdirs==4.5.1
Requires-Dist: pyserial==3.5
Requires-Dist: yamale==6.1.0
